findatamarket/__init__.py
findatamarket/client.py
findatamarket-1.0.0.dist-info/LICENSE
findatamarket-1.0.0.dist-info/METADATA
findatamarket-1.0.0.dist-info/WHEEL
findatamarket-1.0.0.dist-info/top_level.txt
findatamarket-1.0.0.dist-info/RECORD
