Metadata-Version: 2.1
Name: findatamarket
Version: 1.0.0
Summary: SDK for getting financial data from findata.market
Home-page: https://github.com/findata-market/python-sdk
Author: Serkin Alexander
Author-email: serkin.alexander@gmail.com
Classifier: Programming Language :: Python :: 3
Classifier: License :: OSI Approved :: MIT License
Classifier: Operating System :: OS Independent
Requires-Python: >=3.6
License-File: LICENSE
Requires-Dist: requests
Requires-Dist: pandas
